PyJPDF/__init__.py
PyJPDF/pyjpdf.py
PyJPDF/utils.py
PyJPDF-0.1.4.dist-info/LICENSE
PyJPDF-0.1.4.dist-info/METADATA
PyJPDF-0.1.4.dist-info/WHEEL
PyJPDF-0.1.4.dist-info/top_level.txt
PyJPDF-0.1.4.dist-info/RECORD
