Metadata-Version: 2.1
Name: PyJPDF
Version: 0.1.4
Summary: A simple library to extract text from PDF files.
Home-page: https://github.com/LordWaif/PyJPDF
Author: Jasson Carvalho
License: UNKNOWN
Platform: UNKNOWN
Classifier: Development Status :: 3 - Alpha
Classifier: Intended Audience :: Developers
Classifier: License :: OSI Approved :: MIT License
Classifier: Programming Language :: Python :: 3
Classifier: Programming Language :: Python :: 3.6
Classifier: Programming Language :: Python :: 3.7
Classifier: Programming Language :: Python :: 3.8
Classifier: Programming Language :: Python :: 3.9
Classifier: Programming Language :: Python :: 3.10
Requires-Python: >=3.6
Requires-Dist: pyperclip
Requires-Dist: selenium
Requires-Dist: webdriver-manager
